bibmanager/__init__.py
bibmanager/__main__.py
bibmanager/config
bibmanager/version.py
bibmanager/ads_manager/__init__.py
bibmanager/ads_manager/ads_manager.py
bibmanager/bib_manager/__init__.py
bibmanager/bib_manager/bib_manager.py
bibmanager/bib_manager/browser.py
bibmanager/config_manager/__init__.py
bibmanager/config_manager/config_manager.py
bibmanager/examples/aastex62.cls
bibmanager/examples/apj_hyperref.bst
bibmanager/examples/sample.bib
bibmanager/examples/sample.tex
bibmanager/examples/top-apj.tex
bibmanager/latex_manager/__init__.py
bibmanager/latex_manager/latex_manager.py
bibmanager/pdf_manager/__init__.py
bibmanager/pdf_manager/pdf_manager.py
bibmanager/utils/__init__.py
bibmanager/utils/utils.py
bibmanager-1.4.13.dist-info/licenses/LICENSE
bibmanager-1.4.13.dist-info/METADATA
bibmanager-1.4.13.dist-info/WHEEL
bibmanager-1.4.13.dist-info/entry_points.txt
bibmanager-1.4.13.dist-info/top_level.txt
bibmanager-1.4.13.dist-info/RECORD
