Metadata-Version: 2.4
Name: bibmanager
Version: 1.4.13
Summary: A BibTeX manager for LaTeX projects
Author-email: Patricio Cubillos <pcubillos@fulbrightmail.org>
License-Expression: MIT
Project-URL: Homepage, https://github.com/pcubillos/bibmanager
Requires-Python: >=3.9
License-File: LICENSE
Requires-Dist: numpy>=2.0.0
Requires-Dist: requests>=2.19.1
Requires-Dist: packaging>=17.1
Requires-Dist: prompt_toolkit>=3.0.48
Requires-Dist: pygments>=2.2.0
Provides-Extra: test
Requires-Dist: requests-mock; extra == "test"
Requires-Dist: pygments>=2.11; extra == "test"
Dynamic: license-file
